mpv_remote_app/__init__.py
mpv_remote_app/media_controllers.py
mpv_remote_app/media_server.py
mpv_remote_app/windows_monkeypatch.py
mpv_remote_app-0.0.5.dist-info/LICENSE
mpv_remote_app-0.0.5.dist-info/METADATA
mpv_remote_app-0.0.5.dist-info/WHEEL
mpv_remote_app-0.0.5.dist-info/entry_points.txt
mpv_remote_app-0.0.5.dist-info/top_level.txt
mpv_remote_app-0.0.5.dist-info/RECORD
