Metadata-Version: 2.1
Name: mpv-remote-app
Version: 0.0.5
Summary: Server for the Android application
Home-page: https://github.com/mcastorina/mpv-remote-app
Author: miccah
Author-email: m.castorina93@gmail.com
License: UNKNOWN
Platform: UNKNOWN
Classifier: Programming Language :: Python :: 3
Classifier: License :: OSI Approved :: GNU General Public License v3 (GPLv3)
Classifier: Operating System :: OS Independent
Requires-Python: >=3
License-File: LICENSE
Requires-Dist: psutil
